discoverable_tph_280/.config.yaml
discoverable_tph_280/__init__.py
discoverable_tph_280/__main__.py
discoverable_tph_280/barometer.py
discoverable_tph_280/base.py
discoverable_tph_280/bme_280.py
discoverable_tph_280/config.py
discoverable_tph_280/hygrometer.py
discoverable_tph_280/logging.conf
discoverable_tph_280/thermometer.py
discoverable_tph_280/util.py
discoverable_tph_280-0.1.8.dist-info/LICENSE
discoverable_tph_280-0.1.8.dist-info/METADATA
discoverable_tph_280-0.1.8.dist-info/WHEEL
discoverable_tph_280-0.1.8.dist-info/RECORD
