Metadata-Version: 2.1
Name: discoverable-tph-280
Version: 0.1.8
Summary: ha-mqtt-discoverable project to get temperature, pressure and humidity from a bme280 chip
License: Apache 2.0
Author: Tim Daley
Author-email: timdaley@earthling.net
Requires-Python: >=3.11,<4.0
Classifier: License :: Other/Proprietary License
Classifier: Programming Language :: Python :: 3
Classifier: Programming Language :: Python :: 3.11
Requires-Dist: db-sqlite3 (>=0.0.1,<0.0.2)
Requires-Dist: ha-mqtt-discoverable (>=0.9.0,<0.10.0)
Requires-Dist: pre-commit (>=3.3.3,<4.0.0)
Requires-Dist: pydantic-yaml (>=0.11.2,<0.12.0)
Requires-Dist: pysqlite3 (>=0.5.1,<0.6.0)
Requires-Dist: rpi-bme280 (>=0.2.4,<0.3.0)
Requires-Dist: smbus2 (>=0.4.2,<0.5.0)
